purerpc/__init__.py
purerpc/_version.py
purerpc/client.py
purerpc/grpc_proto.py
purerpc/grpc_socket.py
purerpc/rpc.py
purerpc/server.py
purerpc/test_utils.py
purerpc/utils.py
purerpc/wrappers.py
purerpc/grpclib/__init__.py
purerpc/grpclib/_h2_monkeypatch.py
purerpc/grpclib/buffers.py
purerpc/grpclib/config.py
purerpc/grpclib/connection.py
purerpc/grpclib/events.py
purerpc/grpclib/exceptions.py
purerpc/grpclib/headers.py
purerpc/grpclib/status.py
purerpc/protoc_plugin/__init__.py
purerpc/protoc_plugin/plugin.py
purerpc-0.8.0.dist-info/LICENSE
purerpc-0.8.0.dist-info/METADATA
purerpc-0.8.0.dist-info/WHEEL
purerpc-0.8.0.dist-info/entry_points.txt
purerpc-0.8.0.dist-info/top_level.txt
purerpc-0.8.0.dist-info/RECORD
