Metadata-Version: 2.1
Name: purerpc
Version: 0.8.0
Summary: Native, async Python gRPC client and server implementation supporting asyncio, uvloop, trio
Home-page: https://github.com/python-trio/purerpc
Author: Andrew Stepanov
License: Apache License Version 2.0
Keywords: async,await,grpc,pure-python,pypy,network,rpc,http2
Platform: UNKNOWN
Classifier: Development Status :: 4 - Beta
Classifier: Intended Audience :: Developers
Classifier: Intended Audience :: Telecommunications Industry
Classifier: License :: OSI Approved :: Apache Software License
Classifier: Operating System :: MacOS
Classifier: Operating System :: MacOS :: MacOS X
Classifier: Operating System :: POSIX :: BSD
Classifier: Operating System :: POSIX :: Linux
Classifier: Programming Language :: Python
Classifier: Programming Language :: Python :: 3 :: Only
Classifier: Programming Language :: Python :: 3.7
Classifier: Programming Language :: Python :: 3.8
Classifier: Programming Language :: Python :: 3.9
Classifier: Programming Language :: Python :: 3.10
Classifier: Programming Language :: Python :: Implementation :: CPython
Classifier: Programming Language :: Python :: Implementation :: PyPy
Classifier: Framework :: AsyncIO
Classifier: Framework :: Trio
Classifier: Topic :: Internet
Classifier: Topic :: Internet :: WWW/HTTP
Classifier: Topic :: Internet :: WWW/HTTP :: HTTP Servers
Classifier: Topic :: Software Development :: Libraries
Classifier: Topic :: Software Development :: Code Generators
Classifier: Topic :: Software Development :: Libraries :: Python Modules
Classifier: Topic :: System :: Networking
Requires-Python: >=3.7
License-File: LICENSE
Requires-Dist: h2 (<4,>=3.1.0)
Requires-Dist: anyio (>=3.0.0)
Requires-Dist: async-generator (>=1.10)
Provides-Extra: dev
Requires-Dist: pytest ; extra == 'dev'
Requires-Dist: grpcio ; extra == 'dev'
Requires-Dist: grpcio-tools ; extra == 'dev'
Requires-Dist: tblib (>=1.3.2) ; extra == 'dev'
Requires-Dist: trio (>=0.11) ; extra == 'dev'
Requires-Dist: pip-tools (>=6.3.1) ; extra == 'dev'
Requires-Dist: python-forge (>=18.6) ; extra == 'dev'
Requires-Dist: trustme ; extra == 'dev'
Requires-Dist: uvloop ; (platform_system != "Windows") and extra == 'dev'
Provides-Extra: grpc
Requires-Dist: grpcio-tools ; extra == 'grpc'
Provides-Extra: grpc-pypy
Requires-Dist: grpcio (<=1.26) ; extra == 'grpc-pypy'
Requires-Dist: grpcio-tools (<=1.26) ; extra == 'grpc-pypy'
